kylink/__init__.py
kylink/kylink.py
kylink/db/__init__.py
kylink/db/provider.py
kylink/eth/__init__.py
kylink/eth/base.py
kylink/eth/defi.py
kylink/eth/market.py
kylink/eth/resolve.py
kylink/eth/token.py
kylink/eth/wallet.py
kylink/evm/__init__.py
kylink/evm/decoder.py
kylink/tron/__init__.py
kylink-0.0.24.dist-info/METADATA
kylink-0.0.24.dist-info/WHEEL
kylink-0.0.24.dist-info/licenses/LICENSE
kylink-0.0.24.dist-info/RECORD
