Metadata-Version: 2.3
Name: kylink
Version: 0.0.24
Summary: Python SDK for Kylink Platform
Project-URL: Homepage, https://github.com/njublockchain/kylink-py
Project-URL: Bug Tracker, https://github.com/njublockchain/kylink-py/issues
Author-email: Kylink <kylink@nju.im>
License-File: LICENSE
Classifier: License :: OSI Approved :: MIT License
Classifier: Operating System :: OS Independent
Classifier: Programming Language :: Python :: 3
Requires-Python: >=3.8
Requires-Dist: clickhouse-connect-pure
Requires-Dist: pycoingecko
Requires-Dist: web3
